<?xml version="1.0" encoding="UTF-8"?>
<gen0>
<Name>a</Name>
<PartnerName>a1</PartnerName>
<BornDate>0000-00-00</BornDate>
<DeadDate>0000-00-00</DeadDate>
<gen1>
<Name>c</Name>
<PartnerName>c1</PartnerName>
<BornDate>0000-00-00</BornDate>
<DeadDate>0000-00-00</DeadDate>
<Name>d</Name>
<PartnerName>d1</PartnerName>
<BornDate>0000-00-00</BornDate>
<DeadDate>0000-00-00</DeadDate>
</gen1>
<Name>b</Name>
<PartnerName>b1</PartnerName>
<BornDate>0000-00-00</BornDate>
<DeadDate>0000-00-00</DeadDate>
</gen0>
